{
    "TOKEN": "EC-5S353482HH4132909",
    "BILLINGAGREEMENTACCEPTEDSTATUS": "1",
    "CHECKOUTSTATUS": "PaymentActionNotInitiated",
    "TIMESTAMP": "2021-02-01T17:38:31Z",
    "CORRELATIONID": "79cec267ad0b9",
    "ACK": "Success",
    "VERSION": "123",
    "BUILD": "55303704",
    "EMAIL": "sb-fljj24599986@personal.example.com",
    "PAYERID": "D6LDMRKDJ8KZU",
    "PAYERSTATUS": "verified",
    "FIRSTNAME": "John",
    "LASTNAME": "Doe",
    "COUNTRYCODE": "IN",
    "ADDRESSSTATUS": "Confirmed",
    "CURRENCYCODE": "INR",
    "AMT": "134.00",
    "ITEMAMT": "134.00",
    "SHIPPINGAMT": "0.00",
    "HANDLINGAMT": "0.00",
    "TAXAMT": "0.00",
    "DESC": "Order #sdBH-1682 Bill",
    "INVNUM": "sdBH-1682",
    "INSURANCEAMT": "0.00",
    "SHIPDISCAMT": "0.00",
    "INSURANCEOPTIONOFFERED": "false",
    "L_NAME0": "Gemstones",
    "L_NAME1": "Gold Gem",
    "L_QTY0": "1",
    "L_QTY1": "1",
    "L_TAXAMT0": "0.00",
    "L_TAXAMT1": "0.00",
    "L_AMT0": "35.00",
    "L_AMT1": "99.00",
    "PAYMENTREQUEST_0_CURRENCYCODE": "INR",
    "PAYMENTREQUEST_0_AMT": "134.00",
    "PAYMENTREQUEST_0_ITEMAMT": "134.00",
    "PAYMENTREQUEST_0_SHIPPINGAMT": "0.00",
    "PAYMENTREQUEST_0_HANDLINGAMT": "0.00",
    "PAYMENTREQUEST_0_TAXAMT": "0.00",
    "PAYMENTREQUEST_0_DESC": "Order #sdBH-1682 Bill",
    "PAYMENTREQUEST_0_INVNUM": "sdBH-1682",
    "PAYMENTREQUEST_0_INSURANCEAMT": "0.00",
    "PAYMENTREQUEST_0_SHIPDISCAMT": "0.00",
    "PAYMENTREQUEST_0_SELLERPAYPALACCOUNTID": "sb-h3o1p4588387@business.example.com",
    "PAYMENTREQUEST_0_INSURANCEOPTIONOFFERED": "false",
    "L_PAYMENTREQUEST_0_NAME0": "Gemstones",
    "L_PAYMENTREQUEST_0_NAME1": "Gold Gem",
    "L_PAYMENTREQUEST_0_QTY0": "1",
    "L_PAYMENTREQUEST_0_QTY1": "1",
    "L_PAYMENTREQUEST_0_TAXAMT0": "0.00",
    "L_PAYMENTREQUEST_0_TAXAMT1": "0.00",
    "L_PAYMENTREQUEST_0_AMT0": "35.00",
    "L_PAYMENTREQUEST_0_AMT1": "99.00",
    "PAYMENTREQUESTINFO_0_ERRORCODE": "0"
}